Workbook

Sheet Resumen
A1: Investigación de keywords — FreshFinder (28/09/2026)
A2: Documento único, regenerado cada día: todas las frases investigadas (todos los días), el histórico y las recomendadas por el ML, puntuadas con el modelo y los datos actuales de la memoria. Cada frase aparece una vez por producto. 'Primera vez' = día en que se investigó.
A4: Producto | B4: Hoja | C4: Frases | D4: Pasan filtro (ACOS pred. ≤ 30 %) | E4: Cerca (30–35 %) | F4: Ya en campañas | G4: Nuevas hoy
A5: Pinza (B0DCZS1NR6) | B5: Pinza (B0DCZS1NR6) | C5: =COUNTA('Pinza (B0DCZS1NR6)'!A:A)-1 | D5: =COUNTIF('Pinza (B0DCZS1NR6)'!N:N,"Sí") | E5: =COUNTIFS('Pinza (B0DCZS1NR6)'!N:N,"No",'Pinza (B0DCZS1NR6)'!M:M,">0.30",'Pinza (B0DCZS1NR6)'!M:M,"<=0.35") | F5: =COUNTIF('Pinza (B0DCZS1NR6)'!J:J,"Sí") | G5: =COUNTIF('Pinza (B0DCZS1NR6)'!B:B,"2026-09-28")
A6: Rejilla (B0DHYBY6MS) | B6: Rejilla (B0DHYBY6MS) | C6: =COUNTA('Rejilla (B0DHYBY6MS)'!A:A)-1 | D6: =COUNTIF('Rejilla (B0DHYBY6MS)'!N:N,"Sí") | E6: =COUNTIFS('Rejilla (B0DHYBY6MS)'!N:N,"No",'Rejilla (B0DHYBY6MS)'!M:M,">0.30",'Rejilla (B0DHYBY6MS)'!M:M,"<=0.35") | F6: =COUNTIF('Rejilla (B0DHYBY6MS)'!J:J,"Sí") | G6: =COUNTIF('Rejilla (B0DHYBY6MS)'!B:B,"2026-09-28")
A7: Total | C7: =SUM(C5:C6) | D7: =SUM(D5:D6) | E7: =SUM(E5:E6) | F7: =SUM(F5:F6) | G7: =SUM(G5:G6)
A9: Cómo leerlo
A10: Verde | B10: Pasa el filtro del agente: entra en la siguiente ronda si hay hueco en un grupo ACTIVO.
A11: Amarillo | B11: Cerca del filtro (ACOS predicho 30–35 %).
A12: P(compra|clic) | B12: Probabilidad de compra por clic del modelo de ML entrenado con tu histórico.
A13: ACOS predicho | B13: CPC estimado ÷ (P × ticket medio). Filtro del agente: ≤ 30 %.
A14: Foto, no fórmula | B14: Se recalcula al regenerar (cada día, con la rutina). El agente además repuntúa en cada ronda.
A16: Fuentes
A17: Términos de búsqueda propios | B17: Búsquedas reales antes de clicar tus anuncios (Amazon Ads vía AdLabs).
A18: Histórico (vendió) | B18: Tus keywords con al menos 1 compra.
A19: Recomendada ML | B19: Frases nuevas del modelo de keywords.
A20: Autocompletado Amazon | B20: Sugerencias reales del buscador de amazon.es.
A21: Constructor Amazon Ads | B21: Sugeridas por Amazon para el ASIN, con puja.
A22: RMIQ (IA) | B22: Generadas por IA: sin volumen, hipótesis.
A23: Reseñas competencia | B23: Cómo describen el producto los compradores.
A24: Google Trends | B24: Tendencia y temporada en Google España.
A26: Filtros | B26: Solo español; sin marcas ni modelos de coche; fuera lo que el producto no es; 'sin imán' sí vale.
A27: Ojo | B27: 'Homologado' / 'DGT': solo si el producto lo cumple de verdad.

Sheet Pinza (B0DCZS1NR6)
A1: Frase | B1: Primera vez | C1: Fuentes | D1: Nº fuentes | E1: Señal de volumen | F1: Puja sugerida Amazon (€) | G1: Histórico clics | H1: Histórico compras | I1: Histórico ACOS | J1: En campañas | K1: P(compra|clic) modelo | L1: CPC estimado (€) | M1: ACOS predicho | N1: ¿Pasa filtro? | O1: Puja propuesta (€) | P1: Motivo
A2: soporte móvil coche pinza ajustable 360 | B2: — | C2: Recomendada ML | D2: 1 | J2: No | K2: 0.1157 | L2: 0.29 | M2: 0.223 | N2: Sí | O2: 0.39 | P2: entra si hay hueco en un grupo del producto
A3: soporte movil coche pinza fuerte | B3: 2026-09-28 | C3: RMIQ (IA) | D3: 1 | E3: volumen desconocido | J3: No | K3: 0.1144 | L3: 0.29 | M3: 0.226 | N3: Sí | O3: 0.39 | P3: entra si hay hueco en un grupo del producto
A4: soporte teléfono móvil coche pinza para salpicadero | B4: 2026-09-28 | C4: Constructor Amazon Ads | D4: 1 | E4: volumen IS 0 | F4: 0.24 | J4: No | K4: 0.0844 | L4: 0.24 | M4: 0.253 | N4: Sí | O4: 0.28 | P4: entra si hay hueco en un grupo del producto
A5: soporte telefono movil para coche de pinza | B5: 2026-09-28 | C5: Autocompletado Amazon | D5: 1 | E5: volumen alto | J5: No | K5: 0.0801 | L5: 0.29 | M5: 0.322 | N5: No | O5: 0.27 | P5: ACOS predicho 32% > 30%
A6: porta móvil coche pinza 360 | B6: — | C6: Recomendada ML | D6: 1 | J6: No | K6: 0.0696 | L6: 0.29 | M6: 0.371 | N6: No | O6: 0.23 | P6: ACOS predicho 37% > 30%
A7: porta movil coche pinza | B7: 2026-09-28 | C7: Autocompletado Amazon | D7: 1 | E7: volumen bajo | J7: No | K7: 0.0687 | L7: 0.29 | M7: 0.375 | N7: No | O7: 0.23 | P7: ACOS predicho 38% > 30%
A8: soporte gps coche pinza | B8: 2026-09-28 | C8: Reseñas competencia | D8: 1 | J8: No | K8: 0.0604 | L8: 0.29 | M8: 0.427 | N8: No | O8: 0.2 | P8: ACOS predicho 43% > 30%
A9: soporte telefono coche pinza | B9: 2026-09-28 | C9: Autocompletado Amazon, Recomendada ML | D9: 2 | E9: volumen alto | J9: No | K9: 0.054 | L9: 0.29 | M9: 0.478 | N9: No | O9: 0.18 | P9: ACOS predicho 48% > 30%
A10: soporte movil coche a presion | B10: 2026-09-28 | C10: Constructor Amazon Ads | D10: 1 | E10: volumen IS 0 | F10: 0.2 | J10: No | K10: 0.0348 | L10: 0.2 | M10: 0.511 | N10: No | O10: 0.12 | P10: ACOS predicho 51% > 30%
A11: soporte coche pinza | B11: 2026-09-28 | C11: Constructor Amazon Ads | D11: 1 | E11: volumen IS 0 | F11: 0.34 | J11: No | K11: 0.0571 | L11: 0.34 | M11: 0.53 | N11: No | O11: 0.19 | P11: ACOS predicho 53% > 30%
A12: porta teléfono coche pinza para salpicadero | B12: — | C12: Recomendada ML | D12: 1 | J12: No | K12: 0.0479 | L12: 0.29 | M12: 0.539 | N12: No | O12: 0.16 | P12: ACOS predicho 54% > 30%
A13: soporte movil de pinza para salpicadero | B13: 2026-09-28 | C13: Autocompletado Amazon | D13: 1 | E13: volumen medio | J13: No | K13: 0.0407 | L13: 0.29 | M13: 0.634 | N13: No | O13: 0.14 | P13: ACOS predicho 63% > 30%
A14: soporte movil pinza giratorio | B14: 2026-09-28 | C14: Autocompletado Amazon | D14: 1 | E14: volumen medio | J14: No | K14: 0.0395 | L14: 0.29 | M14: 0.653 | N14: No | O14: 0.13 | P14: ACOS predicho 65% > 30%
A15: soporte móvil de pinza antideslizante | B15: — | C15: Recomendada ML | D15: 1 | J15: No | K15: 0.0395 | L15: 0.29 | M15: 0.653 | N15: No | O15: 0.13 | P15: ACOS predicho 65% > 30%
A16: pinza sujecion movil coche | B16: 2026-09-28 | C16: RMIQ (IA) | D16: 1 | E16: volumen desconocido | J16: No | K16: 0.0368 | L16: 0.29 | M16: 0.701 | N16: No | O16: 0.12 | P16: ACOS predicho 70% > 30%
A17: pinza movil coche | B17: 2026-09-28 | C17: Autocompletado Amazon | D17: 1 | E17: volumen alto | J17: No | K17: 0.0359 | L17: 0.29 | M17: 0.719 | N17: No | O17: 0.12 | P17: ACOS predicho 72% > 30%
A18: soporte movil coche 360 | B18: 2026-09-28 | C18: Constructor Amazon Ads | D18: 1 | E18: volumen IS 0 | F18: 0.29 | J18: No | K18: 0.0343 | L18: 0.29 | M18: 0.751 | N18: No | O18: 0.12 | P18: ACOS predicho 75% > 30%
A19: soporte movil 360 grados | B19: 2026-09-28 | C19: Constructor Amazon Ads | D19: 1 | E19: volumen IS 0 | F19: 0.24 | J19: No | K19: 0.0247 | L19: 0.24 | M19: 0.865 | N19: No | O19: 0.08 | P19: ACOS predicho 87% > 30%
A20: soporte movil 360 | B20: 2026-09-28 | C20: Constructor Amazon Ads | D20: 1 | E20: volumen IS 0 | F20: 0.24 | J20: No | K20: 0.0241 | L20: 0.24 | M20: 0.888 | N20: No | O20: 0.08 | P20: ACOS predicho 89% > 30%
A21: pinza movil gps coche | B21: 2026-09-28 | C21: Reseñas competencia | D21: 1 | J21: No | K21: 0.0289 | L21: 0.29 | M21: 0.892 | N21: No | O21: 0.1 | P21: ACOS predicho 89% > 30%
A22: soporte movil coche mechero | B22: 2026-09-28 | C22: Constructor Amazon Ads | D22: 1 | E22: volumen IS 0 | F22: 0.36 | J22: No | K22: 0.0348 | L22: 0.36 | M22: 0.921 | N22: No | O22: 0.12 | P22: ACOS predicho 92% > 30%
A23: mpow soporte movil coche | B23: 2026-09-28 | C23: Constructor Amazon Ads | D23: 1 | E23: volumen IS 0 | F23: 0.37 | J23: No | K23: 0.0348 | L23: 0.37 | M23: 0.946 | N23: No | O23: 0.12 | P23: ACOS predicho 95% > 30%
A24: topk soporte movil coche | B24: 2026-09-28 | C24: Constructor Amazon Ads | D24: 1 | E24: volumen IS 0 | F24: 0.37 | J24: No | K24: 0.0348 | L24: 0.37 | M24: 0.946 | N24: No | O24: 0.12 | P24: ACOS predicho 95% > 30%
A25: soporte para tlf movil coche | B25: 2026-09-28 | C25: Constructor Amazon Ads | D25: 1 | E25: volumen IS 0 | F25: 0.29 | J25: No | K25: 0.0259 | L25: 0.29 | M25: 0.997 | N25: No | O25: 0.09 | P25: ACOS predicho 100% > 30%
A26: pinza movil salpicadero | B26: 2026-09-28 | C26: Reseñas competencia | D26: 1 | J26: No | K26: 0.0257 | L26: 0.29 | M26: 1.003 | N26: No | O26: 0.09 | P26: ACOS predicho 100% > 30%
A27: soporte movil giratorio coche | B27: 2026-09-28 | C27: Constructor Amazon Ads | D27: 1 | E27: volumen IS 0 | F27: 0.34 | J27: No | K27: 0.0273 | L27: 0.34 | M27: 1.106 | N27: No | O27: 0.09 | P27: ACOS predicho 111% > 30%
A28: soporte multifuncional movil coche | B28: 2026-09-28 | C28: Constructor Amazon Ads | D28: 1 | E28: volumen IS 0 | F28: 0.34 | J28: No | K28: 0.0259 | L28: 0.34 | M28: 1.169 | N28: No | O28: 0.09 | P28: ACOS predicho 117% > 30%
A29: soporte universal movil coche | B29: 2026-09-28 | C29: Constructor Amazon Ads | D29: 1 | E29: volumen IS 0 | F29: 0.34 | J29: No | K29: 0.0259 | L29: 0.34 | M29: 1.169 | N29: No | O29: 0.09 | P29: ACOS predicho 117% > 30%
A30: sujeta móvil de pinza para espejo retrovisor | B30: — | C30: Recomendada ML | D30: 1 | J30: No | K30: 0.0189 | L30: 0.29 | M30: 1.369 | N30: No | O30: 0.06 | P30: ACOS predicho 137% > 30%
A31: soporte teléfono salpicadero | B31: 2026-09-28 | C31: Constructor Amazon Ads | D31: 1 | E31: volumen IS 0 | F31: 0.23 | J31: No | K31: 0.0147 | L31: 0.23 | M31: 1.39 | N31: No | O31: 0.05 | P31: ACOS predicho 139% > 30%
A32: soporte smartphone coche | B32: 2026-09-28 | C32: Constructor Amazon Ads | D32: 1 | E32: volumen IS 0 | F32: 0.32 | J32: No | K32: 0.0176 | L32: 0.32 | M32: 1.616 | N32: No | O32: 0.06 | P32: ACOS predicho 162% > 30%
A33: soporte salpicadero | B33: 2026-09-28 | C33: Constructor Amazon Ads | D33: 1 | E33: volumen IS 0 | F33: 0.29 | J33: No | K33: 0.0156 | L33: 0.29 | M33: 1.649 | N33: No | O33: 0.05 | P33: ACOS predicho 165% > 30%
A34: soporte giratorio movil | B34: 2026-09-28 | C34: Constructor Amazon Ads | D34: 1 | E34: volumen IS 0 | F34: 0.34 | J34: No | K34: 0.0181 | L34: 0.34 | M34: 1.674 | N34: No | O34: 0.06 | P34: ACOS predicho 167% > 30%
A35: soporte ajustable para movil | B35: 2026-09-28 | C35: Constructor Amazon Ads | D35: 1 | E35: volumen IS 0 | F35: 0.34 | J35: No | K35: 0.0181 | L35: 0.34 | M35: 1.674 | N35: No | O35: 0.06 | P35: ACOS predicho 167% > 30%
A36: soporte telefono movil | B36: 2026-09-28 | C36: Constructor Amazon Ads | D36: 1 | E36: volumen IS 0 | F36: 0.33 | J36: No | K36: 0.0166 | L36: 0.33 | M36: 1.773 | N36: No | O36: 0.06 | P36: ACOS predicho 177% > 30%
A37: soporte iphone coche | B37: 2026-09-28 | C37: Constructor Amazon Ads | D37: 1 | E37: volumen IS 0 | F37: 0.4 | J37: No | K37: 0.0176 | L37: 0.4 | M37: 2.02 | N37: No | O37: 0.06 | P37: ACOS predicho 202% > 30%
A38: portamovil para el coche | B38: 2026-09-28 | C38: Constructor Amazon Ads | D38: 1 | E38: volumen IS 0 | F38: 0.34 | J38: No | K38: 0.0137 | L38: 0.34 | M38: 2.205 | N38: No | O38: 0.05 | P38: ACOS predicho 220% > 30%
A39: porta celular para coche | B39: 2026-09-28 | C39: Constructor Amazon Ads | D39: 1 | E39: volumen IS 0 | F39: 0.35 | J39: No | K39: 0.0141 | L39: 0.35 | M39: 2.211 | N39: No | O39: 0.05 | P39: ACOS predicho 221% > 30%
A40: sujeta telefono coche | B40: 2026-09-28 | C40: Constructor Amazon Ads | D40: 1 | E40: volumen IS 0 | F40: 0.34 | J40: No | K40: 0.0114 | L40: 0.34 | M40: 2.649 | N40: No | O40: 0.04 | P40: ACOS predicho 265% > 30%
A41: soporte movil coche espejo retrovisor | B41: 2026-09-28 | C41: Autocompletado Amazon | D41: 1 | E41: volumen bajo | J41: No | K41: 0.0357 | L41: 1.07 | M41: 2.667 | N41: No | O41: 0.12 | P41: ACOS predicho 267% > 30%
A42: soporte movil coche sin iman | B42: 2026-09-28 | C42: RMIQ (IA) | D42: 1 | E42: volumen desconocido | J42: No | K42: 0.0357 | L42: 1.07 | M42: 2.667 | N42: No | O42: 0.12 | P42: ACOS predicho 267% > 30%
A43: soporte movil coche sin adhesivo | B43: 2026-09-28 | C43: RMIQ (IA) | D43: 1 | E43: volumen desconocido | J43: No | K43: 0.0357 | L43: 1.07 | M43: 2.667 | N43: No | O43: 0.12 | P43: ACOS predicho 267% > 30%
A44: soporte movil coche parasol ajustable | B44: 2026-09-28 | C44: RMIQ (IA) | D44: 1 | E44: volumen desconocido | J44: No | K44: 0.0357 | L44: 1.07 | M44: 2.667 | N44: No | O44: 0.12 | P44: ACOS predicho 267% > 30%
A45: soporte movil coche sin imanes | B45: 2026-09-28 | C45: RMIQ (IA) | D45: 1 | E45: volumen desconocido | J45: No | K45: 0.0357 | L45: 1.07 | M45: 2.667 | N45: No | O45: 0.12 | P45: ACOS predicho 267% > 30%
A46: soporte movil coche resistente al calor | B46: 2026-09-28 | C46: Reseñas competencia | D46: 1 | J46: No | K46: 0.0357 | L46: 1.07 | M46: 2.667 | N46: No | O46: 0.12 | P46: ACOS predicho 267% > 30%
A47: soporte movil coche consola central | B47: 2026-09-28 | C47: Reseñas competencia | D47: 1 | J47: No | K47: 0.0357 | L47: 1.07 | M47: 2.667 | N47: No | O47: 0.12 | P47: ACOS predicho 267% > 30%
A48: soporte movil coche vertical y horizontal | B48: 2026-09-28 | C48: Reseñas competencia | D48: 1 | J48: No | K48: 0.0357 | L48: 1.07 | M48: 2.667 | N48: No | O48: 0.12 | P48: ACOS predicho 267% > 30%
A49: soporte movil coche giro 360 | B49: 2026-09-28 | C49: RMIQ (IA) | D49: 1 | E49: volumen desconocido | J49: No | K49: 0.0352 | L49: 1.07 | M49: 2.702 | N49: No | O49: 0.12 | P49: ACOS predicho 270% > 30%
A50: soporte movil coche con pinzas | B50: 2026-09-28 | C50: Términos de búsqueda propios, Autocompletado Amazon | D50: 2 | E50: volumen alto | J50: No | K50: 0.0348 | L50: 1.07 | M50: 2.736 | N50: No | O50: 0.12 | P50: ACOS predicho 274% > 30%
A51: soporte movil coche dunlop | B51: 2026-09-28 | C51: Constructor Amazon Ads | D51: 1 | E51: volumen IS 0 | J51: No | K51: 0.0348 | L51: 1.07 | M51: 2.736 | N51: No | O51: 0.12 | P51: ACOS predicho 274% > 30%
A52: soporte movil coche antideslizante | B52: 2026-09-28 | C52: RMIQ (IA) | D52: 1 | E52: volumen desconocido | J52: No | K52: 0.0348 | L52: 1.07 | M52: 2.736 | N52: No | O52: 0.12 | P52: ACOS predicho 274% > 30%
A53: soporte movil coche estable | B53: 2026-09-28 | C53: RMIQ (IA) | D53: 1 | E53: volumen desconocido | J53: No | K53: 0.0348 | L53: 1.07 | M53: 2.736 | N53: No | O53: 0.12 | P53: ACOS predicho 274% > 30%
A54: soporte movil coche ajustable | B54: 2026-09-28 | C54: RMIQ (IA) | D54: 1 | E54: volumen desconocido | J54: No | K54: 0.0348 | L54: 1.07 | M54: 2.736 | N54: No | O54: 0.12 | P54: ACOS predicho 274% > 30%
A55: soporte movil coche multiusos | B55: 2026-09-28 | C55: RMIQ (IA) | D55: 1 | E55: volumen desconocido | J55: No | K55: 0.0348 | L55: 1.07 | M55: 2.736 | N55: No | O55: 0.12 | P55: ACOS predicho 274% > 30%
A56: soporte movil coche homologado | B56: 2026-09-28 | C56: Google Trends | D56: 1 | J56: No | K56: 0.0348 | L56: 1.07 | M56: 2.736 | N56: No | O56: 0.12 | P56: ACOS predicho 274% > 30%
A57: soporte movil coche dgt | B57: 2026-09-28 | C57: Google Trends | D57: 1 | J57: No | K57: 0.0348 | L57: 1.07 | M57: 2.736 | N57: No | O57: 0.12 | P57: ACOS predicho 274% > 30%
A58: soporte movil coche salpicadero rugoso | B58: 2026-09-28 | C58: Autocompletado Amazon | D58: 1 | E58: volumen alto | J58: No | K58: 0.0344 | L58: 1.07 | M58: 2.769 | N58: No | O58: 0.12 | P58: ACOS predicho 277% > 30%
A59: soporte movil coche salpicadero curvo | B59: 2026-09-28 | C59: Autocompletado Amazon | D59: 1 | E59: volumen medio | J59: No | K59: 0.0344 | L59: 1.07 | M59: 2.769 | N59: No | O59: 0.12 | P59: ACOS predicho 277% > 30%
A60: soporte movil coche salpicadero giratorio | B60: 2026-09-28 | C60: Autocompletado Amazon | D60: 1 | E60: volumen alto | J60: No | K60: 0.0344 | L60: 1.07 | M60: 2.769 | N60: No | O60: 0.12 | P60: ACOS predicho 277% > 30%
A61: soporte movil parasol coche | B61: 2026-09-28 | C61: Autocompletado Amazon, Recomendada ML | D61: 2 | E61: volumen alto | J61: No | K61: 0.0273 | L61: 1.07 | M61: 3.482 | N61: No | O61: 0.09 | P61: ACOS predicho 348% > 30%
A62: soporte movil retrovisor coche | B62: 2026-09-28 | C62: Autocompletado Amazon | D62: 1 | E62: volumen alto | J62: No | K62: 0.0273 | L62: 1.07 | M62: 3.482 | N62: No | O62: 0.09 | P62: ACOS predicho 348% > 30%
A63: soporte movil guantera coche | B63: 2026-09-28 | C63: Reseñas competencia | D63: 1 | J63: No | K63: 0.0273 | L63: 1.07 | M63: 3.482 | N63: No | O63: 0.09 | P63: ACOS predicho 348% > 30%
A64: soporte movil salpicadero no se cae | B64: 2026-09-28 | C64: Reseñas competencia | D64: 1 | J64: No | K64: 0.0263 | L64: 1.07 | M64: 3.625 | N64: No | O64: 0.09 | P64: ACOS predicho 362% > 30%
A65: soporte movil salpicadero encima del volante | B65: 2026-09-28 | C65: Reseñas competencia | D65: 1 | J65: No | K65: 0.0256 | L65: 1.07 | M65: 3.72 | N65: No | O65: 0.09 | P65: ACOS predicho 372% > 30%
A66: soporte movil espejo retrovisor | B66: 2026-09-28 | C66: Autocompletado Amazon | D66: 1 | E66: volumen bajo | J66: No | K66: 0.025 | L66: 1.07 | M66: 3.807 | N66: No | O66: 0.08 | P66: ACOS predicho 381% > 30%
A67: soporte movil retrovisor ajustable | B67: 2026-09-28 | C67: RMIQ (IA) | D67: 1 | E67: volumen desconocido | J67: No | K67: 0.025 | L67: 1.07 | M67: 3.807 | N67: No | O67: 0.08 | P67: ACOS predicho 381% > 30%
A68: soporte movil cuadro de instrumentos | B68: 2026-09-28 | C68: Reseñas competencia | D68: 1 | J68: No | K68: 0.025 | L68: 1.07 | M68: 3.807 | N68: No | O68: 0.08 | P68: ACOS predicho 381% > 30%
A69: soporte movil salpicadero curvo | B69: 2026-09-28 | C69: Autocompletado Amazon | D69: 1 | E69: volumen alto | J69: No | K69: 0.0249 | L69: 1.07 | M69: 3.818 | N69: No | O69: 0.08 | P69: ACOS predicho 382% > 30%
A70: soporte movil tapa salpicadero | B70: 2026-09-28 | C70: Reseñas competencia | D70: 1 | J70: No | K70: 0.0249 | L70: 1.07 | M70: 3.818 | N70: No | O70: 0.08 | P70: ACOS predicho 382% > 30%
A71: soporte movil retrovisor | B71: 2026-09-28 | C71: Autocompletado Amazon | D71: 1 | E71: volumen alto | J71: No | K71: 0.0244 | L71: 1.07 | M71: 3.907 | N71: No | O71: 0.08 | P71: ACOS predicho 391% > 30%
A72: soporte movil woolcar | B72: 2026-09-28 | C72: Constructor Amazon Ads | D72: 1 | E72: volumen IS 0 | J72: No | K72: 0.0244 | L72: 1.07 | M72: 3.907 | N72: No | O72: 0.08 | P72: ACOS predicho 391% > 30%
A73: soporte movil universal | B73: 2026-09-28 | C73: RMIQ (IA) | D73: 1 | E73: volumen desconocido | J73: No | K73: 0.0244 | L73: 1.07 | M73: 3.907 | N73: No | O73: 0.08 | P73: ACOS predicho 391% > 30%
A74: soporte movil parasol | B74: 2026-09-28 | C74: RMIQ (IA) | D74: 1 | E74: volumen desconocido | J74: No | K74: 0.0244 | L74: 1.07 | M74: 3.907 | N74: No | O74: 0.08 | P74: ACOS predicho 391% > 30%
A75: soporte coche pda | B75: 2026-09-28 | C75: Constructor Amazon Ads | D75: 1 | E75: volumen IS 0 | J75: No | K75: 0.0171 | L75: 1.07 | M75: 5.584 | N75: No | O75: 0.06 | P75: ACOS predicho 558% > 30%
A76: soporte telefono movil salpicadero | B76: 2026-09-28 | C76: Autocompletado Amazon | D76: 1 | E76: volumen alto | J76: No | K76: 0.017 | L76: 1.07 | M76: 5.615 | N76: No | O76: 0.06 | P76: ACOS predicho 562% > 30%
A77: soporte movil clip | B77: 2026-09-28 | C77: Constructor Amazon Ads | D77: 1 | E77: volumen IS 0 | F77: 0.46 | J77: No | K77: 0.0244 | L77: 0.46 | N77: No | P77: lleva palabras de otro producto tuyo
A78: soporte movil coche | B78: 2026-09-28 | C78: RMIQ (IA), Histórico (vendió) | D78: 2 | E78: volumen desconocido; 52 clics, 1 compras (Amplia); 24 clics, 1 compras (Frase) | G78: 114 | H78: 2 | I78: 3.8328756 | J78: Sí | K78: 0.0339 | L78: 1.07 | N78: No | P78: ya está en tus campañas
A79: soporte movil salpicadero | B79: 2026-09-28 | C79: RMIQ (IA) | D79: 1 | E79: volumen desconocido | G79: 0 | H79: 0 | J79: Sí | K79: 0.0243 | L79: 1.07 | N79: No | P79: ya está en tus campañas
A80: soporte movil coche pinza | B80: 2026-09-28 | C80: Términos de búsqueda propios, RMIQ (IA), Histórico (vendió) | D80: 3 | E80: volumen desconocido; 205 clics, 20 compras (Frase); 24 clics, 6 compras (Frase); 31 clics, 3 compras (Amplia); 18 clics, 2 compras (Amplia); | G80: 307 | H80: 34 | I80: 0.41312416 | J80: Sí | K80: 0.1117 | L80: 0.29 | N80: No | P80: ya está en tus campañas
A81: soporte telefono coche | B81: 2026-09-28 | C81: RMIQ (IA) | D81: 1 | E81: volumen desconocido | G81: 3 | H81: 0 | J81: Sí | K81: 0.0157 | L81: 1.07 | N81: No | P81: ya está en tus campañas
A82: soporte movil salpicadero coche | B82: 2026-09-28 | C82: RMIQ (IA) | D82: 1 | E82: volumen desconocido | G82: 1 | H82: 0 | J82: Sí | K82: 0.0273 | L82: 1.07 | N82: No | P82: ya está en tus campañas
A83: soporte movil coche facil instalacion | B83: 2026-09-28 | C83: RMIQ (IA) | D83: 1 | E83: volumen desconocido | J83: Sí | K83: 0.0357 | L83: 1.07 | N83: No | P83: ya está en tus campañas
A84: soporte movil coche sin ventosa | B84: 2026-09-28 | C84: RMIQ (IA) | D84: 1 | E84: volumen desconocido | J84: Sí | K84: 0.0357 | L84: 1.07 | N84: No | P84: ya está en tus campañas
A85: sujeta móvil para coche pinza | B85: 2026-09-28 | C85: Términos de búsqueda propios, Recomendada ML | D85: 2 | E85: volumen 1 clics / 0 compras | G85: 4 | H85: 0 | J85: Sí | K85: 0.0541 | L85: 0.29 | N85: No | P85: ya está en tus campañas
A86: soporte móvil para coche de pinza para salpicadero | B86: — | C86: Histórico (vendió), Recomendada ML | D86: 2 | E86: 9 clics, 1 compras (Amplia) | G86: 9 | H86: 1 | I86: 0.30028874 | J86: Sí | K86: 0.1175 | L86: 0.29 | N86: No | P86: ya está en tus campañas
A87: soporte móvil coche pinza para espejo retrovisor | B87: — | C87: Recomendada ML | D87: 1 | J87: Sí | K87: 0.1171 | L87: 0.29 | N87: No | P87: ya está en tus campañas

Sheet Rejilla (B0DHYBY6MS)
A1: Frase | B1: Primera vez | C1: Fuentes | D1: Nº fuentes | E1: Señal de volumen | F1: Puja sugerida Amazon (€) | G1: Histórico clics | H1: Histórico compras | I1: Histórico ACOS | J1: En campañas | K1: P(compra|clic) modelo | L1: CPC estimado (€) | M1: ACOS predicho | N1: ¿Pasa filtro? | O1: Puja propuesta (€) | P1: Motivo
A2: soporte telefono para rejilla ventilacion redonda | B2: 2026-09-28 | C2: Términos de búsqueda propios | D2: 1 | E2: volumen 1 clics / 0 compras | J2: No | K2: 0.1123 | L2: 0.31 | M2: 0.194 | N2: Sí | O2: 0.48 | P2: entra si hay hueco en un grupo del producto
A3: soporte telefono rejilla ventilación coche | B3: 2026-09-28 | C3: Autocompletado Amazon | D3: 1 | E3: volumen alto | J3: No | K3: 0.1051 | L3: 0.31 | M3: 0.207 | N3: Sí | O3: 0.45 | P3: entra si hay hueco en un grupo del producto
A4: soporte telefono para rejilla aire | B4: 2026-09-28 | C4: Términos de búsqueda propios | D4: 1 | E4: volumen 1 clics / 0 compras | J4: No | K4: 0.0883 | L4: 0.31 | M4: 0.246 | N4: Sí | O4: 0.38 | P4: entra si hay hueco en un grupo del producto
A5: soporte telefono coche rejilla | B5: 2026-09-28 | C5: Términos de búsqueda propios, Autocompletado Amazon | D5: 2 | E5: volumen alto | J5: No | K5: 0.0686 | L5: 0.31 | M5: 0.317 | N5: No | O5: 0.29 | P5: ACOS predicho 32% > 30%
A6: soporte telefono coche rejilla redonda | B6: 2026-09-28 | C6: Autocompletado Amazon | D6: 1 | E6: volumen alto | J6: No | K6: 0.0656 | L6: 0.31 | M6: 0.331 | N6: No | O6: 0.28 | P6: ACOS predicho 33% > 30%
A7: soporte movil coche ventilación redonda | B7: 2026-09-28 | C7: Autocompletado Amazon | D7: 1 | E7: volumen medio | J7: No | K7: 0.0624 | L7: 0.31 | M7: 0.348 | N7: No | O7: 0.27 | P7: ACOS predicho 35% > 30%
A8: soporte movil coche ventilacion vertical | B8: 2026-09-28 | C8: Autocompletado Amazon | D8: 1 | E8: volumen alto | J8: No | K8: 0.0624 | L8: 0.31 | M8: 0.348 | N8: No | O8: 0.27 | P8: ACOS predicho 35% > 30%
A9: soporte movil ventilacion | B9: 2026-09-28 | C9: Autocompletado Amazon | D9: 1 | E9: volumen alto | J9: No | K9: 0.0562 | L9: 0.31 | M9: 0.387 | N9: No | O9: 0.24 | P9: ACOS predicho 39% > 30%
A10: porta móvil de rejilla ajustable 360 | B10: — | C10: Recomendada ML | D10: 1 | J10: No | K10: 0.0546 | L10: 0.31 | M10: 0.398 | N10: No | O10: 0.23 | P10: ACOS predicho 40% > 30%
A11: soporte movil ventilacion redonda | B11: 2026-09-28 | C11: Autocompletado Amazon | D11: 1 | E11: volumen alto | J11: No | K11: 0.0537 | L11: 0.31 | M11: 0.405 | N11: No | O11: 0.23 | P11: ACOS predicho 41% > 30%
A12: soporte movil rejilla ventilacion redonda | B12: 2026-09-28 | C12: Autocompletado Amazon | D12: 1 | E12: volumen bajo | J12: No | K12: 0.053 | L12: 0.31 | M12: 0.41 | N12: No | O12: 0.23 | P12: ACOS predicho 41% > 30%
A13: soporte de telefono para coche rejilla de aire iphone | B13: 2026-09-28 | C13: Autocompletado Amazon | D13: 1 | E13: volumen medio | J13: No | K13: 0.0517 | L13: 0.31 | M13: 0.42 | N13: No | O13: 0.22 | P13: ACOS predicho 42% > 30%
A14: soporte movil rejilla redonda | B14: 2026-09-28 | C14: Autocompletado Amazon, Reseñas competencia | D14: 2 | E14: volumen alto | J14: No | K14: 0.05 | L14: 0.31 | M14: 0.435 | N14: No | O14: 0.21 | P14: ACOS predicho 43% > 30%
A15: soporte movil rejilla circular | B15: 2026-09-28 | C15: Autocompletado Amazon | D15: 1 | E15: volumen medio | J15: No | K15: 0.05 | L15: 0.31 | M15: 0.435 | N15: No | O15: 0.21 | P15: ACOS predicho 43% > 30%
A16: soporte movil rejilla vertical | B16: 2026-09-28 | C16: Autocompletado Amazon | D16: 1 | E16: volumen bajo | J16: No | K16: 0.05 | L16: 0.31 | M16: 0.435 | N16: No | O16: 0.21 | P16: ACOS predicho 43% > 30%
A17: soporte movil coche doble gancho | B17: 2026-09-28 | C17: Autocompletado Amazon, Reseñas competencia | D17: 2 | E17: volumen bajo | J17: No | K17: 0.0471 | L17: 0.31 | M17: 0.462 | N17: No | O17: 0.2 | P17: ACOS predicho 46% > 30%
A18: soporte movil coche clip gancho | B18: 2026-09-28 | C18: RMIQ (IA) | D18: 1 | E18: volumen desconocido | J18: No | K18: 0.0471 | L18: 0.31 | M18: 0.462 | N18: No | O18: 0.2 | P18: ACOS predicho 46% > 30%
A19: soporte movil rejilla no se cae | B19: 2026-09-28 | C19: Reseñas competencia | D19: 1 | J19: No | K19: 0.0456 | L19: 0.31 | M19: 0.477 | N19: No | O19: 0.2 | P19: ACOS predicho 48% > 30%
A20: soporte movil rejilla coche universal | B20: 2026-09-28 | C20: Autocompletado Amazon | D20: 1 | E20: volumen bajo | J20: No | K20: 0.0445 | L20: 0.31 | M20: 0.488 | N20: No | O20: 0.19 | P20: ACOS predicho 49% > 30%
A21: soporte movil coche rejilla redonda | B21: 2026-09-28 | C21: Autocompletado Amazon | D21: 1 | E21: volumen alto | J21: No | K21: 0.0439 | L21: 0.31 | M21: 0.495 | N21: No | O21: 0.19 | P21: ACOS predicho 49% > 30%
A22: soporte movil coche rejilla vertical | B22: 2026-09-28 | C22: Autocompletado Amazon | D22: 1 | E22: volumen alto | J22: No | K22: 0.0439 | L22: 0.31 | M22: 0.495 | N22: No | O22: 0.19 | P22: ACOS predicho 49% > 30%
A23: soporte movil coche rejilla circular | B23: 2026-09-28 | C23: Autocompletado Amazon | D23: 1 | E23: volumen bajo | J23: No | K23: 0.0439 | L23: 0.31 | M23: 0.495 | N23: No | O23: 0.19 | P23: ACOS predicho 49% > 30%
A24: soporte movil coche rejilla horizontal | B24: 2026-09-28 | C24: Autocompletado Amazon | D24: 1 | E24: volumen bajo | J24: No | K24: 0.0439 | L24: 0.31 | M24: 0.495 | N24: No | O24: 0.19 | P24: ACOS predicho 49% > 30%
A25: soporte movil coche gancho metalico | B25: 2026-09-28 | C25: Autocompletado Amazon | D25: 1 | E25: volumen alto | J25: No | K25: 0.0437 | L25: 0.31 | M25: 0.497 | N25: No | O25: 0.19 | P25: ACOS predicho 50% > 30%
A26: sujeta movil coche rejilla | B26: 2026-09-28 | C26: Autocompletado Amazon | D26: 1 | E26: volumen alto | J26: No | K26: 0.0433 | L26: 0.31 | M26: 0.502 | N26: No | O26: 0.19 | P26: ACOS predicho 50% > 30%
A27: soporte móvil rejilla coche ajustable 360 | B27: — | C27: Recomendada ML | D27: 1 | J27: No | K27: 0.0425 | L27: 0.31 | M27: 0.511 | N27: No | O27: 0.18 | P27: ACOS predicho 51% > 30%
A28: soporte movil coche salida de aire | B28: 2026-09-28 | C28: Reseñas competencia | D28: 1 | J28: No | K28: 0.0417 | L28: 0.31 | M28: 0.521 | N28: No | O28: 0.18 | P28: ACOS predicho 52% > 30%
A29: soporte movil rejilla aire | B29: 2026-09-28 | C29: Autocompletado Amazon | D29: 1 | E29: volumen medio | J29: No | K29: 0.0411 | L29: 0.31 | M29: 0.529 | N29: No | O29: 0.18 | P29: ACOS predicho 53% > 30%
A30: soporte movil coche rejilla gancho metalico | B30: 2026-09-28 | C30: Autocompletado Amazon | D30: 1 | E30: volumen medio | J30: No | K30: 0.0389 | L30: 0.31 | M30: 0.558 | N30: No | O30: 0.17 | P30: ACOS predicho 56% > 30%
A31: soporte movil coche rejilla circular gancho | B31: 2026-09-28 | C31: Autocompletado Amazon | D31: 1 | E31: volumen alto | J31: No | K31: 0.0389 | L31: 0.31 | M31: 0.558 | N31: No | O31: 0.17 | P31: ACOS predicho 56% > 30%
A32: soporte telefono ventilador coche | B32: 2026-09-28 | C32: Reseñas competencia | D32: 1 | J32: No | K32: 0.0383 | L32: 0.32 | M32: 0.586 | N32: No | O32: 0.16 | P32: ACOS predicho 59% > 30%
A33: soporte movil rejilla aire acondicionado | B33: 2026-09-28 | C33: Reseñas competencia | D33: 1 | J33: No | K33: 0.0364 | L33: 0.31 | M33: 0.598 | N33: No | O33: 0.16 | P33: ACOS predicho 60% > 30%
A34: soporte movil coche rejilla aire | B34: 2026-09-28 | C34: Autocompletado Amazon | D34: 1 | E34: volumen medio | J34: No | K34: 0.0361 | L34: 0.31 | M34: 0.602 | N34: No | O34: 0.15 | P34: ACOS predicho 60% > 30%
A35: soporte movil toma de aire coche | B35: 2026-09-28 | C35: Reseñas competencia | D35: 1 | J35: No | K35: 0.0354 | L35: 0.31 | M35: 0.615 | N35: No | O35: 0.15 | P35: ACOS predicho 61% > 30%
A36: soporte movil coche para rejilla redonda de aire | B36: 2026-09-28 | C36: Autocompletado Amazon | D36: 1 | E36: volumen medio | J36: No | K36: 0.0345 | L36: 0.31 | M36: 0.63 | N36: No | O36: 0.15 | P36: ACOS predicho 63% > 30%
A37: soporte movil coche aire redondo | B37: 2026-09-28 | C37: Autocompletado Amazon | D37: 1 | E37: volumen alto | J37: No | K37: 0.0343 | L37: 0.31 | M37: 0.634 | N37: No | O37: 0.15 | P37: ACOS predicho 63% > 30%
A38: soporte movil clip | B38: 2026-09-28 | C38: Constructor Amazon Ads | D38: 1 | E38: volumen IS 0 | F38: 0.46 | J38: No | K38: 0.0506 | L38: 0.46 | M38: 0.637 | N38: No | O38: 0.22 | P38: ACOS predicho 64% > 30%
A39: soporte movil coche fijo | B39: 2026-09-28 | C39: Constructor Amazon Ads | D39: 1 | E39: volumen IS 0 | F39: 0.24 | J39: No | K39: 0.0254 | L39: 0.24 | M39: 0.662 | N39: No | O39: 0.11 | P39: ACOS predicho 66% > 30%
A40: soporte movil 360 | B40: 2026-09-28 | C40: Constructor Amazon Ads | D40: 1 | E40: volumen IS 0 | F40: 0.24 | J40: No | K40: 0.0242 | L40: 0.24 | M40: 0.696 | N40: No | O40: 0.1 | P40: ACOS predicho 70% > 30%
A41: soporte movil coche aire acondicionado vertical | B41: 2026-09-28 | C41: Autocompletado Amazon | D41: 1 | E41: volumen medio | J41: No | K41: 0.0303 | L41: 0.31 | M41: 0.717 | N41: No | O41: 0.13 | P41: ACOS predicho 72% > 30%
A42: soporte movil 360 grados | B42: 2026-09-28 | C42: Constructor Amazon Ads | D42: 1 | E42: volumen IS 0 | F42: 0.24 | J42: No | K42: 0.0231 | L42: 0.24 | M42: 0.729 | N42: No | O42: 0.1 | P42: ACOS predicho 73% > 30%
A43: porta telefono para coche | B43: 2026-09-28 | C43: Constructor Amazon Ads | D43: 1 | E43: volumen IS 0 | F43: 0.34 | J43: No | K43: 0.032 | L43: 0.34 | M43: 0.744 | N43: No | O43: 0.14 | P43: ACOS predicho 74% > 30%
A44: soporte movil coche fashion | B44: 2026-09-28 | C44: Constructor Amazon Ads | D44: 1 | E44: volumen IS 0 | F44: 0.28 | J44: No | K44: 0.0254 | L44: 0.28 | M44: 0.772 | N44: No | O44: 0.11 | P44: ACOS predicho 77% > 30%
A45: sujeta telefono coche | B45: 2026-09-28 | C45: Constructor Amazon Ads | D45: 1 | E45: volumen IS 0 | F45: 0.34 | J45: No | K45: 0.0307 | L45: 0.34 | M45: 0.778 | N45: No | O45: 0.13 | P45: ACOS predicho 78% > 30%
A46: soporte movil coche grande | B46: 2026-09-28 | C46: Constructor Amazon Ads | D46: 1 | E46: volumen IS 0 | F46: 0.29 | J46: No | K46: 0.0254 | L46: 0.29 | M46: 0.8 | N46: No | O46: 0.11 | P46: ACOS predicho 80% > 30%
A47: soporte movil coche 360 | B47: 2026-09-28 | C47: Constructor Amazon Ads | D47: 1 | E47: volumen IS 0 | F47: 0.29 | J47: No | K47: 0.0254 | L47: 0.29 | M47: 0.8 | N47: No | O47: 0.11 | P47: ACOS predicho 80% > 30%
A48: soporte movil coche aireador | B48: 2026-09-28 | C48: Autocompletado Amazon | D48: 1 | E48: volumen medio | J48: No | K48: 0.0254 | L48: 0.32 | M48: 0.883 | N48: No | O48: 0.11 | P48: ACOS predicho 88% > 30%
A49: soporte movil coche eono | B49: 2026-09-28 | C49: Constructor Amazon Ads | D49: 1 | E49: volumen IS 0 | J49: No | K49: 0.0254 | L49: 0.32 | M49: 0.883 | N49: No | O49: 0.11 | P49: ACOS predicho 88% > 30%
A50: mejor soporte movil coche | B50: 2026-09-28 | C50: RMIQ (IA) | D50: 1 | E50: volumen desconocido | J50: No | K50: 0.0254 | L50: 0.32 | M50: 0.883 | N50: No | O50: 0.11 | P50: ACOS predicho 88% > 30%
A51: soporte movil coche seguro | B51: 2026-09-28 | C51: RMIQ (IA) | D51: 1 | E51: volumen desconocido | J51: No | K51: 0.0254 | L51: 0.32 | M51: 0.883 | N51: No | O51: 0.11 | P51: ACOS predicho 88% > 30%
A52: soporte movil coche antivibracion | B52: 2026-09-28 | C52: RMIQ (IA) | D52: 1 | E52: volumen desconocido | J52: No | K52: 0.0254 | L52: 0.32 | M52: 0.883 | N52: No | O52: 0.11 | P52: ACOS predicho 88% > 30%
A53: soporte movil coche para baches | B53: 2026-09-28 | C53: RMIQ (IA) | D53: 1 | E53: volumen desconocido | J53: No | K53: 0.0254 | L53: 0.32 | M53: 0.883 | N53: No | O53: 0.11 | P53: ACOS predicho 88% > 30%
A54: soporte movil coche con funda | B54: 2026-09-28 | C54: Reseñas competencia | D54: 1 | J54: No | K54: 0.0254 | L54: 0.32 | M54: 0.883 | N54: No | O54: 0.11 | P54: ACOS predicho 88% > 30%
A55: soporte movil coche homologado | B55: 2026-09-28 | C55: Google Trends | D55: 1 | J55: No | K55: 0.0254 | L55: 0.32 | M55: 0.883 | N55: No | O55: 0.11 | P55: ACOS predicho 88% > 30%
A56: soporte movil coche dgt | B56: 2026-09-28 | C56: Google Trends | D56: 1 | J56: No | K56: 0.0254 | L56: 0.32 | M56: 0.883 | N56: No | O56: 0.11 | P56: ACOS predicho 88% > 30%
A57: soporte smartphone coche | B57: 2026-09-28 | C57: Constructor Amazon Ads | D57: 1 | E57: volumen IS 0 | F57: 0.32 | J57: No | K57: 0.0243 | L57: 0.32 | M57: 0.922 | N57: No | O57: 0.1 | P57: ACOS predicho 92% > 30%
A58: soporte movil coche aireador redondo | B58: 2026-09-28 | C58: Autocompletado Amazon | D58: 1 | E58: volumen bajo | J58: No | K58: 0.0242 | L58: 0.32 | M58: 0.925 | N58: No | O58: 0.1 | P58: ACOS predicho 93% > 30%
A59: soporte movil coche giro 360 | B59: 2026-09-28 | C59: RMIQ (IA) | D59: 1 | E59: volumen desconocido | J59: No | K59: 0.0242 | L59: 0.32 | M59: 0.925 | N59: No | O59: 0.1 | P59: ACOS predicho 93% > 30%
A60: soporte movil coche agarre fuerte | B60: 2026-09-28 | C60: RMIQ (IA) | D60: 1 | E60: volumen desconocido | J60: No | K60: 0.0242 | L60: 0.32 | M60: 0.925 | N60: No | O60: 0.1 | P60: ACOS predicho 93% > 30%
A61: soporte movil coche alta resistencia | B61: 2026-09-28 | C61: RMIQ (IA) | D61: 1 | E61: volumen desconocido | J61: No | K61: 0.0242 | L61: 0.32 | M61: 0.925 | N61: No | O61: 0.1 | P61: ACOS predicho 93% > 30%
A62: soporte movil coche movil pesado | B62: 2026-09-28 | C62: Reseñas competencia | D62: 1 | J62: No | K62: 0.0242 | L62: 0.32 | M62: 0.925 | N62: No | O62: 0.1 | P62: ACOS predicho 93% > 30%
A63: soporte movil coche c3 | B63: 2026-09-28 | C63: Constructor Amazon Ads | D63: 1 | E63: volumen IS 0 | F63: 0.34 | J63: No | K63: 0.0254 | L63: 0.34 | M63: 0.938 | N63: No | O63: 0.11 | P63: ACOS predicho 94% > 30%
A64: soporte movil coche sencillo | B64: 2026-09-28 | C64: Constructor Amazon Ads | D64: 1 | E64: volumen IS 0 | F64: 0.34 | J64: No | K64: 0.0254 | L64: 0.34 | M64: 0.938 | N64: No | O64: 0.11 | P64: ACOS predicho 94% > 30%
A65: soporte movil coche compatible todos modelos | B65: 2026-09-28 | C65: RMIQ (IA) | D65: 1 | E65: volumen desconocido | J65: No | K65: 0.0231 | L65: 0.32 | M65: 0.97 | N65: No | O65: 0.1 | P65: ACOS predicho 97% > 30%
A66: soporte mobil cotxe | B66: 2026-09-28 | C66: Constructor Amazon Ads | D66: 1 | E66: volumen IS 0 | F66: 0.37 | J66: No | K66: 0.0261 | L66: 0.37 | M66: 0.993 | N66: No | O66: 0.11 | P66: ACOS predicho 99% > 30%
A67: soporte móvil viaje coche | B67: 2026-09-28 | C67: Términos de búsqueda propios | D67: 1 | E67: volumen 1 clics / 0 compras | J67: No | K67: 0.0215 | L67: 0.32 | M67: 1.045 | N67: No | O67: 0.09 | P67: ACOS predicho 104% > 30%
A68: porta celular para coche | B68: 2026-09-28 | C68: Constructor Amazon Ads | D68: 1 | E68: volumen IS 0 | F68: 0.35 | J68: No | K68: 0.0232 | L68: 0.35 | M68: 1.056 | N68: No | O68: 0.1 | P68: ACOS predicho 106% > 30%
A69: soporte movil | B69: 2026-09-28 | C69: Constructor Amazon Ads | D69: 1 | E69: volumen IS 0 | F69: 1.24 | J69: No | K69: 0.0254 | L69: 1.24 | M69: 3.428 | N69: No | O69: 0.11 | P69: ACOS predicho 343% > 30%
A70: soporte movil coche | B70: 2026-09-28 | C70: RMIQ (IA), Histórico (vendió) | D70: 2 | E70: volumen desconocido; 498 clics, 20 compras (Amplia); 13 clics, 1 compras (Amplia); 26 clics, 1 compras (Amplia); 4 clics, 1 compras (Exacta) | G70: 554 | H70: 23 | I70: 1.6855257 | J70: Sí | K70: 0.0266 | L70: 0.32 | N70: No | P70: ya está en tus campañas
A71: sujeta movil coche | B71: 2026-09-28 | C71: RMIQ (IA) | D71: 1 | E71: volumen desconocido | G71: 6 | H71: 0 | J71: Sí | K71: 0.025 | L71: 0.32 | N71: No | P71: ya está en tus campañas
A72: soporte movil rejilla ventilacion | B72: 2026-09-28 | C72: RMIQ (IA) | D72: 1 | E72: volumen desconocido | G72: 0 | H72: 0 | J72: Sí | K72: 0.0555 | L72: 0.31 | N72: No | P72: ya está en tus campañas
A73: soporte movil coche universal | B73: 2026-09-28 | C73: RMIQ (IA) | D73: 1 | E73: volumen desconocido | G73: 0 | H73: 0 | J73: Sí | K73: 0.0254 | L73: 0.32 | N73: No | P73: ya está en tus campañas
A74: soporte movil coche estable | B74: 2026-09-28 | C74: RMIQ (IA) | D74: 1 | E74: volumen desconocido | G74: 0 | H74: 0 | J74: Sí | K74: 0.0254 | L74: 0.32 | N74: No | P74: ya está en tus campañas
A75: soporte movil coche 360 grados | B75: 2026-09-28 | C75: RMIQ (IA) | D75: 1 | E75: volumen desconocido | G75: 0 | H75: 0 | J75: Sí | K75: 0.0242 | L75: 0.32 | N75: No | P75: ya está en tus campañas
A76: soporte movil ventilacion coche | B76: 2026-09-28 | C76: RMIQ (IA), Histórico (vendió) | D76: 2 | E76: volumen desconocido; 9 clics, 1 compras (Frase) | G76: 13 | H76: 1 | I76: 0.7264387 | J76: Sí | K76: 0.05 | L76: 0.31 | N76: No | P76: ya está en tus campañas
A77: soporte movil coche ajustable | B77: 2026-09-28 | C77: RMIQ (IA) | D77: 1 | E77: volumen desconocido | G77: 0 | H77: 0 | J77: Sí | K77: 0.0254 | L77: 0.32 | N77: No | P77: ya está en tus campañas
A78: soporte movil coche rejilla | B78: 2026-09-28 | C78: RMIQ (IA) | D78: 1 | E78: volumen desconocido | G78: 4 | H78: 0 | J78: Sí | K78: 0.046 | L78: 0.31 | N78: No | P78: ya está en tus campañas
A79: soporte movil coche fuerte | B79: 2026-09-28 | C79: RMIQ (IA) | D79: 1 | E79: volumen desconocido | G79: 0 | H79: 0 | J79: Sí | K79: 0.0254 | L79: 0.32 | N79: No | P79: ya está en tus campañas
A80: soporte movil coche sin iman | B80: 2026-09-28 | C80: RMIQ (IA) | D80: 1 | E80: volumen desconocido | G80: 0 | H80: 0 | J80: Sí | K80: 0.0242 | L80: 0.32 | N80: No | P80: ya está en tus campañas
A81: soporte movil coche sujecion firme | B81: 2026-09-28 | C81: RMIQ (IA) | D81: 1 | E81: volumen desconocido | G81: 0 | H81: 0 | J81: Sí | K81: 0.0242 | L81: 0.32 | N81: No | P81: ya está en tus campañas
A82: soporte movil coche sin ventosa | B82: 2026-09-28 | C82: RMIQ (IA) | D82: 1 | E82: volumen desconocido | J82: Sí | K82: 0.0242 | L82: 0.32 | N82: No | P82: ya está en tus campañas
A83: soporte movil coche facil instalacion | B83: 2026-09-28 | C83: RMIQ (IA) | D83: 1 | E83: volumen desconocido | J83: Sí | K83: 0.0242 | L83: 0.32 | N83: No | P83: ya está en tus campañas
A84: soporte movil coche con gancho | B84: 2026-09-28 | C84: Términos de búsqueda propios, RMIQ (IA) | D84: 2 | E84: volumen desconocido | G84: 2 | H84: 0 | J84: Sí | K84: 0.0458 | L84: 0.31 | N84: No | P84: ya está en tus campañas
A85: soporte coche teléfono móvil | B85: 2026-09-28 | C85: Términos de búsqueda propios, Histórico (vendió) | D85: 2 | E85: volumen 9 clics / 3 compras; 22 clics, 4 compras (Exacta) | G85: 24 | H85: 4 | I85: 0.40678704 | J85: Sí | K85: 0.0489 | L85: 0.32 | N85: No | P85: ya está en tus campañas
A86: soporte telefono rejilla ventilacion | B86: 2026-09-28 | C86: Términos de búsqueda propios, Recomendada ML | D86: 2 | E86: volumen 7 clics / 1 compras | J86: Sí | K86: 0.1172 | L86: 0.31 | N86: No | P86: ya está en tus campañas
A87: soporte telefono rejilla | B87: 2026-09-28 | C87: Términos de búsqueda propios, Histórico (vendió) | D87: 2 | E87: volumen 1 clics / 0 compras; 16 clics, 2 compras (Frase) | G87: 16 | H87: 2 | I87: 0.52842201 | J87: Sí | K87: 0.1109 | L87: 0.31 | N87: No | P87: ya está en tus campañas
A88: movil coche | B88: — | C88: Histórico (vendió) | D88: 1 | E88: 142 clics, 9 compras (Amplia) | G88: 142 | H88: 9 | I88: 0.957505 | J88: Sí | K88: 0.0399 | L88: 0.32 | N88: No | P88: ya está en tus campañas
A89: soporte coche | B89: — | C89: Histórico (vendió) | D89: 1 | E89: 124 clics, 5 compras (Amplia) | G89: 124 | H89: 5 | I89: 1.7154103 | J89: Sí | K89: 0.0273 | L89: 0.32 | N89: No | P89: ya está en tus campañas
A90: soporte móvil para coche de pinza | B90: — | C90: Histórico (vendió) | D90: 1 | E90: 72 clics, 5 compras (Exacta) | G90: 90 | H90: 5 | I90: 1.098376 | J90: Sí | K90: 0.0168 | L90: 0.32 | N90: No | P90: ya está en tus campañas
A91: sujeta moviles para coche | B91: — | C91: Histórico (vendió) | D91: 1 | E91: 21 clics, 1 compras (Amplia) | G91: 21 | H91: 1 | I91: 1.6230821 | J91: Sí | K91: 0.0291 | L91: 0.32 | N91: No | P91: ya está en tus campañas
A92: sujetar movil en el coche | B92: — | C92: Histórico (vendió) | D92: 1 | E92: 15 clics, 1 compras (Amplia) | G92: 15 | H92: 1 | I92: 1.4409606 | J92: Sí | K92: 0.0421 | L92: 0.32 | N92: No | P92: ya está en tus campañas
A93: phone holder car | B93: — | C93: Histórico (vendió) | D93: 1 | E93: 13 clics, 1 compras (Amplia) | G93: 13 | H93: 1 | I93: 0.81054036 | J93: Sí | K93: 0.0421 | L93: 0.32 | N93: No | P93: ya está en tus campañas
A94: soporte teléfono rejilla coche con gancho | B94: — | C94: Recomendada ML | D94: 1 | J94: Sí | K94: 0.0826 | L94: 0.31 | N94: No | P94: ya está en tus campañas
A95: rejilla móvil coche | B95: — | C95: Recomendada ML | D95: 1 | J95: Sí | K95: 0.081 | L95: 0.31 | N95: No | P95: ya está en tus campañas
A96: soporte rejilla móvil | B96: — | C96: Recomendada ML | D96: 1 | J96: Sí | K96: 0.0673 | L96: 0.31 | N96: No | P96: ya está en tus campañas
A97: porta móvil de rejilla ventilación | B97: — | C97: Recomendada ML | D97: 1 | J97: Sí | K97: 0.0634 | L97: 0.31 | N97: No | P97: ya está en tus campañas
A98: sujeta móvil de rejilla | B98: — | C98: Recomendada ML | D98: 1 | J98: Sí | K98: 0.0492 | L98: 0.31 | N98: No | P98: ya está en tus campañas

Sheet Términos de búsqueda
A1: Término de búsqueda | B1: Producto (ASIN) | C1: Clics | D1: Compras | E1: Gasto (€) | F1: Ventas (€) | G1: ACOS | H1: Conversión
A2: soporte coche teléfono móvil | B2: B0DHYBY6MS | C2: 9 | D2: 3 | E2: 7.41 | F2: 35.97 | G2: =IF(F2>0,E2/F2,"") | H2: =IF(C2>0,D2/C2,"")
A3: soporte movil coche pinza | B3: B0DCZS1NR6 | C3: 61 | D3: 2 | E3: 34.1 | F3: 22.78 | G3: =IF(F3>0,E3/F3,"") | H3: =IF(C3>0,D3/C3,"")
A4: soporte móvil coche pinza | B4: B0DCZS1NR6 | C4: 15 | D4: 2 | E4: 8.07 | F4: 22.78 | G4: =IF(F4>0,E4/F4,"") | H4: =IF(C4>0,D4/C4,"")
A5: soporte telefono rejilla ventilacion | B5: B0DHYBY6MS | C5: 7 | D5: 1 | E5: 6.94 | F5: 11.99 | G5: =IF(F5>0,E5/F5,"") | H5: =IF(C5>0,D5/C5,"")
A6: soporte movil coche con pinza | B6: B0DCZS1NR6 | C6: 5 | D6: 1 | E6: 1.78 | F6: 11.99 | G6: =IF(F6>0,E6/F6,"") | H6: =IF(C6>0,D6/C6,"")
A7: soporte de movil para coche con pinza | B7: B0DCZS1NR6 | C7: 4 | D7: 0 | E7: 1.27 | F7: 0 | G7: =IF(F7>0,E7/F7,"") | H7: =IF(C7>0,D7/C7,"")
A8: soporte de coche para teléfono móvil | B8: B0DHYBY6MS | C8: 2 | D8: 0 | E8: 1.95 | F8: 0 | G8: =IF(F8>0,E8/F8,"") | H8: =IF(C8>0,D8/C8,"")
A9: soporte para coche para teléfono móvil | B9: B0DHYBY6MS | C9: 2 | D9: 0 | E9: 1.6 | F9: 0 | G9: =IF(F9>0,E9/F9,"") | H9: =IF(C9>0,D9/C9,"")
A10: soporte coche para teléfono móvil | B10: B0DHYBY6MS | C10: 2 | D10: 0 | E10: 1.37 | F10: 0 | G10: =IF(F10>0,E10/F10,"") | H10: =IF(C10>0,D10/C10,"")
A11: soporte para coche telefono movil | B11: B0DHYBY6MS | C11: 2 | D11: 0 | E11: 1.33 | F11: 0 | G11: =IF(F11>0,E11/F11,"") | H11: =IF(C11>0,D11/C11,"")
A12: soporte telefono rejilla coche | B12: B0DHYBY6MS | C12: 2 | D12: 0 | E12: 0.87 | F12: 0 | G12: =IF(F12>0,E12/F12,"") | H12: =IF(C12>0,D12/C12,"")
A13: soporte móvil para coche de pinza | B13: B0DCZS1NR6 | C13: 2 | D13: 0 | E13: 1.26 | F13: 0 | G13: =IF(F13>0,E13/F13,"") | H13: =IF(C13>0,D13/C13,"")
... A29: sujeta móvil para coche pinza | B29: B0DCZS1NR6 | C29: 1 | D29: 0 | E29: 0.24 | F29: 0 | G29: =IF(F29>0,E29/F29,"") | H29: =IF(C29>0,D29/C29,"")
A30: Total | C30: =SUM(C2:C29) | D30: =SUM(D2:D29) | E30: =SUM(E2:E29) | F30: =SUM(F2:F29) | G30: =IF(F30>0,E30/F30,"") | H30: =IF(C30>0,D30/C30,"")
A32: Fuente: términos de búsqueda de Amazon Ads (vía AdLabs), actualizado 2026-09-28. Sin marcas.

Sheet Reseñas competencia
A1: Producto nuestro | B1: ASIN competidor | C1: Competidor | D1: Valoración | E1: Lo que valoran | F1: Lo que critican | G1: Idea para keywords / ficha
A2: Pinza | B2: B07H996QMD | C2: OcioDual – pinza salpicadero | D2: 3,6 ★ (580) | E2: Fácil de poner; encima del cuadro/volante para ver el GPS sin girar la cabeza | F2: Se deforma con el calor y deja de agarrar; se rompe; salta en baches; solo horizontal | G2: 'resistente al calor', 'no se cae en baches', 'vertical y horizontal', 'encima del volante', GPS
A3: Pinza | B3: B09P3SZB6P | C3: AUTOZOCO – salpicadero con resorte | D3: (nº1 en su categoría) | E3: Encaja en la tapa del salpicadero / consola central; buena calidad-precio | F3: Fijación poco segura; no orientable; dudas con el calor | G3: 'consola central', 'tapa salpicadero', 'orientable 360' (si lo es)
A4: Pinza | B4: B08N4KR6PK | C4: BEENLE – salpicadero + retrovisor | D4: — | E4: Gira 360°, robusto, fácil de instalar; se usa en guantera o parasol | F4: Se sale con el movimiento; aprieta los botones del móvil; faltaba el destornillador | G4: 'parasol', 'guantera', 'no pulsa los botones'
A5: Pinza | B5: B0BS1TQJH2 | C5: Sujeta teléfono pinza (gravedad) | D5: — | E5: Ajustable a cada móvil; diseño divertido; se puede cargar | F5: Baja calidad; con funda casi no cabe | G5: 'compatible con funda'
A6: Rejilla | B6: B0DHK6KBGH | C6: miracase – doble gancho metálico | D6: nº1 más vendido | E6: Firme si la rejilla es la adecuada; no daña la rejilla; no se cae con baches | F6: Depende de la forma de la rejilla | G6: 'doble gancho', 'no daña la rejilla', 'no se cae con baches'
A7: Rejilla | B7: B0F3J3QHD7 | C7: GRIFEMA – rejilla cierre automático | D7: 6,99 € | E7: Barato; fácil de instalar; 'Toma de aire' | F7: Se mueve con un móvil pesado | G7: 'toma de aire', 'móvil pesado / grande'
A8: Rejilla | B8: B0C1NK79FK | C8: Blukar – rejilla ventilación | D8: — | E8: Mejor que los de ventosa; sólido; rejilla del aire acondicionado | F8: Pesado; flexa rejillas largas; la rosca de la bola se afloja | G8: 'aire acondicionado', 'mejor que ventosa'
A9: Rejilla | B9: B08CKYFLHQ | C9: Blukar – rejillas de ventilación | D9: — | E9: Dos agarres; gira a horizontal; de toda la vida | F9: Rejillas tipo ruleta (redondas) cuestan | G9: 'rejilla redonda' (si encaja), 'horizontal y vertical'
A11: Fuente: fichas y reseñas visibles en amazon.es, resumidas. Las frases derivadas están en las hojas de producto con fuente 'Reseñas competencia'.

Sheet Google Trends
A1: Google Trends — 'soporte movil coche', España, últimos 5 años (índice 0-100)
A3: Año | B3: Interés medio
A4: 2021 (sep-dic) | B4: 24.5
A5: 2022 | B5: 31
A6: 2023 | B6: 25.9
A7: 2024 | B7: 21
A8: 2025 | B8: 18.8
A9: 2026 (ene-sep) | B9: 15.1
A11: Mes (media 5 años) | B11: Interés medio
A12: Enero | B12: 23.2
A13: Febrero | B13: 20.8
A14: Marzo | B14: 22
A15: Abril | B15: 25.6
A16: Mayo | B16: 21.1
A17: Junio | B17: 21.6
A18: Julio | B18: 26
A19: Agosto | B19: 26.4
A20: Septiembre | B20: 20.5
A21: Octubre | B21: 20.9
A22: Noviembre | B22: 21.2
A23: Diciembre | B23: 24.7
A25: Consultas en ascenso | B25: Crecimiento
A26: soporte móvil coche homologado | B26: +700 %
A27: soporte movil coche dgt | B27: +450 %
A28: soporte homologado movil coche | B28: +300 %
A29: Tema: Homologación | B29: +170 %
A30: Tema: Ventosa | B30: +160 %
A31: Tema: Panel de instrumentos | B31: +130 %
A33: Conclusiones
A34: 1. La búsqueda en Google de 'soporte movil coche' baja cada año (31 en 2022 → 15 en 2026): mercado maduro, hay que ganar con frases específicas, no genéricas.
A35: 2. Picos en julio-agosto (viajes de verano), diciembre (regalos) y Semana Santa. Buen momento para tener stock y subir presupuesto.
A36: 3. Sube 'homologado' / 'DGT': la gente busca soportes legales. Si tu soporte no tapa la visión y cumple, dilo en la ficha (sin inventar homologaciones).
A37: 4. Entre tipos, 'magnético' y 'ventosa' son los más buscados en Google; 'rejilla' crece; 'pinza' casi no tiene volumen en Google (sí en Amazon).
A38: 5. Google Trends no mide Amazon: úsalo para temporada y tendencia, no para decidir pujas.
A40: Mes | B40: Interés
A41: 2021-09 | B41: 23
A42: 2021-10 | B42: 21.8
A43: 2021-11 | B43: 25
A44: 2021-12 | B44: 27.8
A45: 2022-01 | B45: 29.6
A46: 2022-02 | B46: 25.8
A47: 2022-03 | B47: 31.3
A48: 2022-04 | B48: 59
A49: 2022-05 | B49: 28.8
A50: 2022-06 | B50: 31.5
A51: 2022-07 | B51: 34.6
A52: 2022-08 | B52: 33
... A101: 2026-09 | B101: 13
